Metadata-Version: 1.1
Name: rasplivestation
Version: 0.0.1
Summary: It's a usefull little package to launch a stream via the command-line utility Livestreamer : http://docs.livestreamer.io/index.html on a Raspberry Pi
Home-page: UNKNOWN
Author: Krounet
Author-email: krounet@gmail.com
License: WTFPL
Platform: UNKNOWN
Classifier: Programming Language :: Python
Classifier: Development Status :: 1 - Planning
Classifier: License :: OSI Approved
Classifier: Natural Language :: French
Classifier: Operating System :: OS Independent
Classifier: Programming Language :: Python :: 2.7
Classifier: Topic :: Multimedia
